mercantile/__init__.py
mercantile/scripts/__init__.py
mercantile-1.2.0.dist-info/AUTHORS.txt
mercantile-1.2.0.dist-info/LICENSE.txt
mercantile-1.2.0.dist-info/METADATA
mercantile-1.2.0.dist-info/WHEEL
mercantile-1.2.0.dist-info/entry_points.txt
mercantile-1.2.0.dist-info/top_level.txt
mercantile-1.2.0.dist-info/RECORD
