Metadata-Version: 2.1
Name: mercantile
Version: 1.2.0
Summary: Web mercator XYZ tile utilities
Home-page: https://github.com/mapbox/mercantile
Author: Sean Gillies
Author-email: sean@mapbox.com
License: BSD
Keywords: mapping,web mercator,tiles
Platform: UNKNOWN
Classifier: Programming Language :: Python :: 2.7
Classifier: Programming Language :: Python :: 3
Classifier: Development Status :: 5 - Production/Stable
Classifier: Intended Audience :: Developers
Classifier: License :: OSI Approved :: BSD License
Classifier: Operating System :: OS Independent
Classifier: Topic :: Scientific/Engineering :: GIS
Requires-Dist: click (>=3.0)
Provides-Extra: dev
Requires-Dist: check-manifest ; extra == 'dev'
Provides-Extra: test
Requires-Dist: hypothesis ; extra == 'test'
Requires-Dist: pytest ; extra == 'test'
